{
  "actions": [
    {
      "acted_at": "1997-07-24T16:00:00-04:00", 
      "references": [], 
      "text": "Amendment (A012) offered by Mr. Neumann.", 
      "type": "action"
    }, 
    {
      "acted_at": "1997-07-24T17:02:00-04:00", 
      "how": "roll", 
      "references": [], 
      "result": "fail", 
      "roll": 314, 
      "text": "On agreeing to the Neumann amendment (A012) Failed by recorded vote: 185 - 242 (Roll no. 314).", 
      "type": "vote", 
      "vote_type": "vote", 
      "where": "h"
    }
  ], 
  "amendment_id": "hamdt273-105", 
  "amendment_type": "hamdt", 
  "amends_amendment": null, 
  "amends_bill": {
    "bill_id": "hr2160-105", 
    "bill_type": "hr", 
    "congress": 105, 
    "number": 2160
  }, 
  "amends_treaty": null, 
  "chamber": "h", 
  "congress": "105", 
  "description": "Amendment sought to prohibit funding for any nonrecourse loan program for the 1998 crop of quota peanuts with a national average loan rate in excess of $550 per ton.", 
  "house_number": 12, 
  "introduced_at": "1997-07-24", 
  "number": 273, 
  "purpose": "An amendment, printed as amendment No. 17 in the Congressional Record of July 17, 1997, to reduce the price support for peanut crops from $610 per ton to $550 per ton.", 
  "sponsor": {
    "district": "1", 
    "name": "Neumann, Mark W.", 
    "state": "WI", 
    "thomas_id": "00861", 
    "title": "Rep", 
    "type": "person"
  }, 
  "status": "fail", 
  "status_at": "1997-07-24T17:02:00-04:00", 
  "updated_at": "2013-07-17T07:51:36-04:00"
}