{
  "actions": [
    {
      "acted_at": "1999-06-16T21:03:00-04:00", 
      "references": [], 
      "text": "Amendment (A021) offered by Mr. Stearns.", 
      "type": "action"
    }, 
    {
      "acted_at": "1999-06-16T23:32:00-04:00", 
      "how": "roll", 
      "references": [], 
      "result": "pass", 
      "roll": 216, 
      "text": "On agreeing to the Stearns amendment (A021) Agreed to by recorded vote: 293 - 134 (Roll no. 216).", 
      "type": "vote", 
      "vote_type": "vote", 
      "where": "h"
    }
  ], 
  "amendment_id": "hamdt195-106", 
  "amendment_type": "hamdt", 
  "amends_amendment": null, 
  "amends_bill": {
    "bill_id": "hr1501-106", 
    "bill_type": "hr", 
    "congress": 106, 
    "number": 1501
  }, 
  "amends_treaty": null, 
  "chamber": "h", 
  "congress": "106", 
  "description": "Amendment adds a set of Congressional findings with regard to the enforcement of Federal firearm laws.", 
  "house_number": 21, 
  "introduced_at": "1999-06-16", 
  "number": 195, 
  "purpose": "An amendment no. 21 and printed in Part A of H.Rept. 106-186 to establish a set of Congressional findings with regard to the enforcement of Federal firearm violations.", 
  "sponsor": {
    "district": "6", 
    "name": "Stearns, Cliff", 
    "state": "FL", 
    "thomas_id": "01103", 
    "title": "Rep", 
    "type": "person"
  }, 
  "status": "pass", 
  "status_at": "1999-06-16T23:32:00-04:00", 
  "updated_at": "2013-07-17T08:15:42-04:00"
}