{
  "actions": [
    {
      "acted_at": "2004-06-22T16:06:00-04:00", 
      "references": [
        {
          "reference": "CR H4708-4709", 
          "type": "consideration"
        }, 
        {
          "reference": "CR H4708", 
          "type": "text"
        }
      ], 
      "text": "Amendment (A004) offered by Ms. Jackson-Lee (TX).", 
      "type": "action"
    }, 
    {
      "acted_at": "2004-06-22T16:10:00-04:00", 
      "references": [], 
      "text": "By unanimous consent, the Jackson-Lee (TX) amendment was withdrawn.", 
      "type": "action"
    }
  ], 
  "amendment_id": "hamdt596-108", 
  "amendment_type": "hamdt", 
  "amends_amendment": null, 
  "amends_bill": {
    "bill_id": "hr4613-108", 
    "bill_type": "hr", 
    "congress": 108, 
    "number": 4613
  }, 
  "amends_treaty": null, 
  "chamber": "h", 
  "congress": "108", 
  "description": null, 
  "house_number": 4, 
  "introduced_at": "2004-06-22", 
  "number": 596, 
  "purpose": "Amendment seeks to add $10,000,000 for \"Embassy Security, Construction, and Maintenance\" for interim facilities for the United States Mission in Iraq.", 
  "sponsor": {
    "district": "18", 
    "name": "Jackson-Lee, Sheila", 
    "state": "TX", 
    "thomas_id": "00588", 
    "title": "Rep", 
    "type": "person"
  }, 
  "status": "offered", 
  "status_at": "2004-06-22", 
  "updated_at": "2013-07-17T08:16:05-04:00"
}