{
  "actions": [
    {
      "acted_at": "1995-07-20T21:53:00-04:00", 
      "references": [], 
      "text": "Amendment (A021) offered by Mrs. Lowey.", 
      "type": "action"
    }, 
    {
      "acted_at": "1995-07-20T23:19:00-04:00", 
      "references": [], 
      "text": "On agreeing to the Lowey amendment (A021) Failed by recorded vote: 158 - 249, 8 Present (Roll No. 545).", 
      "type": "action"
    }
  ], 
  "amendment_id": "hamdt616-104", 
  "amendment_type": "hamdt", 
  "amends_amendment": null, 
  "amends_bill": {
    "bill_id": "hr1976-104", 
    "bill_type": "hr", 
    "congress": 104, 
    "number": 1976
  }, 
  "amends_treaty": null, 
  "chamber": "h", 
  "congress": "104", 
  "description": "Amendment sought to prohibit the use of funds appropriated in the bill from being used to provide deficiency or land diversion payments to anyone with an annual adjusted gross income of $100,000 or more from off-farm sources.", 
  "house_number": 21, 
  "introduced_at": "1995-07-20", 
  "number": 616, 
  "purpose": "An amendment to prohibit the use of funds appropriated in teh bill from being used to provide deficiency or land diversion payments to anyone with an annual adjusted gross income of $100,000 or more from non-farm income.", 
  "sponsor": {
    "district": "18", 
    "name": "Lowey, Nita M.", 
    "state": "NY", 
    "thomas_id": "00709", 
    "title": "Rep", 
    "type": "person"
  }, 
  "status": "offered", 
  "status_at": "1995-07-20", 
  "updated_at": "2013-07-17T07:50:48-04:00"
}