{
  "actions": [
    {
      "acted_at": "1995-10-10T14:12:00-04:00", 
      "references": [], 
      "text": "Amendment (A001) in the nature of a substitute offered by Mr. Burr.", 
      "type": "action"
    }, 
    {
      "acted_at": "1995-10-10T15:01:00-04:00", 
      "how": "by voice vote", 
      "references": [], 
      "result": "pass", 
      "text": "On agreeing to the Burr amendment (A001) Agreed to by voice vote.", 
      "type": "vote", 
      "vote_type": "vote", 
      "where": "h"
    }
  ], 
  "amendment_id": "hamdt830-104", 
  "amendment_type": "hamdt", 
  "amends_amendment": null, 
  "amends_bill": {
    "bill_id": "hr436-104", 
    "bill_type": "hr", 
    "congress": 104, 
    "number": 436
  }, 
  "amends_treaty": null, 
  "chamber": "h", 
  "congress": "104", 
  "description": "Amendment in the nature of a substitute directs Federal agencies with regulatory responsibilities to differentiate between animal fats or vegetable oils and other types of oils and greases, including petroleum, when writing regulations.", 
  "house_number": 1, 
  "introduced_at": "1995-10-10", 
  "number": 830, 
  "purpose": "An amendment in the nature of a substitute not preprinted in the Congressional Record.", 
  "sponsor": {
    "district": "5", 
    "name": "Burr, Richard", 
    "state": "NC", 
    "thomas_id": "00153", 
    "title": "Rep", 
    "type": "person"
  }, 
  "status": "pass", 
  "status_at": "1995-10-10T15:01:00-04:00", 
  "updated_at": "2013-07-17T07:50:49-04:00"
}