{
  "actions": [
    {
      "acted_at": "1995-01-30T19:56:00-05:00", 
      "references": [], 
      "text": "Amendments (A021) offered by Mr. Clay.", 
      "type": "action"
    }, 
    {
      "acted_at": "1995-01-30T20:19:00-05:00", 
      "references": [], 
      "text": "On agreeing to the Clay amendments (A021) Failed by recorded vote: 138 - 284 (Roll no. 64).", 
      "type": "action"
    }
  ], 
  "amendment_id": "hamdt30-104", 
  "amendment_type": "hamdt", 
  "amends_amendment": null, 
  "amends_bill": {
    "bill_id": "hr5-104", 
    "bill_type": "hr", 
    "congress": 104, 
    "number": 5
  }, 
  "amends_treaty": null, 
  "chamber": "h", 
  "congress": "104", 
  "description": "Amendments en bloc sought to exempt from the provisions of the bill Federal laws that are necessary to protect the health and safety of those, including children and discouraged workers, who, through no fault of their own, receive welfare assistance.", 
  "house_number": 21, 
  "introduced_at": "1995-01-30", 
  "number": 30, 
  "purpose": "An amendment consisting of two amendments, offered en bloc, to exempt from the provisions of the bill those laws and regulations that are necessary to protect the health and safety of those, including children and discouraged workers, who, through no fault of their own, receive welfare assistance. Text of the amendments were printed as amendment Nos. 40 and 42 in the Congressional Record of January 19, 1995.", 
  "sponsor": {
    "district": "1", 
    "name": "Clay, William (Bill)", 
    "state": "MO", 
    "thomas_id": "00203", 
    "title": "Rep", 
    "type": "person"
  }, 
  "status": "offered", 
  "status_at": "1995-01-30", 
  "updated_at": "2013-07-17T07:50:44-04:00"
}