{
  "actions": [
    {
      "acted_at": "2005-10-20", 
      "references": [
        {
          "reference": "CR S11634", 
          "type": "consideration"
        }, 
        {
          "reference": "CR S11634", 
          "type": "text"
        }
      ], 
      "text": "Amendment SA 2175 proposed by Senator Bond.", 
      "type": "action"
    }, 
    {
      "acted_at": "2005-10-20", 
      "how": "Voice Vote", 
      "references": [], 
      "result": "pass", 
      "text": "Amendment SA 2175 agreed to in Senate by Voice Vote.", 
      "type": "vote", 
      "vote_type": "vote", 
      "where": "s"
    }
  ], 
  "amendment_id": "samdt2175-109", 
  "amendment_type": "samdt", 
  "amends_amendment": null, 
  "amends_bill": {
    "bill_id": "hr3058-109", 
    "bill_type": "hr", 
    "congress": 109, 
    "number": 3058
  }, 
  "amends_treaty": null, 
  "chamber": "s", 
  "congress": "109", 
  "description": null, 
  "introduced_at": "2005-10-20", 
  "number": 2175, 
  "proposed_at": "2005-10-20", 
  "purpose": "Of a technical nature.", 
  "sponsor": {
    "district": null, 
    "name": "Bond, Christopher S.", 
    "state": "MO", 
    "thomas_id": "01286", 
    "title": "Sen", 
    "type": "person"
  }, 
  "status": "pass", 
  "status_at": "2005-10-20", 
  "updated_at": "2013-07-17T08:16:12-04:00"
}