{
  "actions": [
    {
      "acted_at": "2007-06-20T13:37:00-04:00", 
      "references": [
        {
          "reference": "CR H6763-6764, H6788-6789", 
          "type": "consideration"
        }, 
        {
          "reference": "CR H6763", 
          "type": "text"
        }
      ], 
      "text": "Amendment (A019) offered by Mr. Neugebauer.", 
      "type": "action"
    }, 
    {
      "acted_at": "2007-06-20T17:38:00-04:00", 
      "how": "roll", 
      "references": [], 
      "result": "fail", 
      "roll": 519, 
      "text": "On agreeing to the Neugebauer amendment (A019) Failed by recorded vote: 133 - 298 (Roll no. 519).", 
      "type": "vote", 
      "vote_type": "vote", 
      "where": "h"
    }
  ], 
  "amendment_id": "hamdt334-110", 
  "amendment_type": "hamdt", 
  "amends_amendment": null, 
  "amends_bill": {
    "bill_id": "hr2641-110", 
    "bill_type": "hr", 
    "congress": 110, 
    "number": 2641
  }, 
  "amends_treaty": null, 
  "chamber": "h", 
  "congress": "110", 
  "description": "Amendment sought to delete funding for the Appalachian Regional Commission.", 
  "house_number": 19, 
  "introduced_at": "2007-06-20", 
  "number": 334, 
  "purpose": "An amendment numbered 17 printed in the Congressional Record to strike the $35 million appropriation for the Appalachian Regional Commission.", 
  "sponsor": {
    "district": "19", 
    "name": "Neugebauer, Randy", 
    "state": "TX", 
    "thomas_id": "01758", 
    "title": "Rep", 
    "type": "person"
  }, 
  "status": "fail", 
  "status_at": "2007-06-20T17:38:00-04:00", 
  "updated_at": "2013-07-17T08:16:32-04:00"
}