{
  "actions": [
    {
      "acted_at": "2005-05-18T15:24:00-04:00", 
      "references": [
        {
          "reference": "CR H3490", 
          "type": "consideration"
        }, 
        {
          "reference": "CR H3490", 
          "type": "text"
        }
      ], 
      "text": "Amendment (A014) offered by Mr. Cardin.", 
      "type": "action"
    }, 
    {
      "acted_at": "2005-05-18T15:27:00-04:00", 
      "how": "by voice vote", 
      "references": [], 
      "result": "pass", 
      "text": "On agreeing to the Cardin amendment (A014) Agreed to by voice vote.", 
      "type": "vote", 
      "vote_type": "vote", 
      "where": "h"
    }
  ], 
  "amendment_id": "hamdt159-109", 
  "amendment_type": "hamdt", 
  "amends_amendment": null, 
  "amends_bill": {
    "bill_id": "hr1817-109", 
    "bill_type": "hr", 
    "congress": 109, 
    "number": 1817
  }, 
  "amends_treaty": null, 
  "chamber": "h", 
  "congress": "109", 
  "description": "Amendment requires the Department of Homeland Security to study and report to Congress on the feasibility and desirability of modifying and updating the existing boundaries of the National Capital Region.", 
  "house_number": 14, 
  "introduced_at": "2005-05-18", 
  "number": 159, 
  "purpose": "An amendment numbered 14 printed in Part B of House Report 109-84 to require the DHS to conduct a study of the feasibility and desirability of expanding the \"National Capitol Region\" (NCR) area beyond its existing boundaries, which were set in 1952. DHS would study whether an expanded NCR would promote coordination between State, regional, and local government and the ability of the Federal, State, and local governments to prevent and respond to a terrorist attack within the NCR.", 
  "sponsor": {
    "district": "3", 
    "name": "Cardin, Benjamin L.", 
    "state": "MD", 
    "thomas_id": "00174", 
    "title": "Rep", 
    "type": "person"
  }, 
  "status": "pass", 
  "status_at": "2005-05-18T15:27:00-04:00", 
  "updated_at": "2013-07-17T08:16:17-04:00"
}