{
  "actions": [
    {
      "acted_at": "2005-09-20", 
      "references": [
        {
          "reference": "CR S10212-10214", 
          "type": "consideration"
        }, 
        {
          "reference": "CR S10212", 
          "type": "text"
        }
      ], 
      "text": "Amendment SA 1738 proposed by Senator Allard.", 
      "type": "action"
    }, 
    {
      "acted_at": "2005-09-20", 
      "how": "Voice Vote", 
      "references": [], 
      "result": "pass", 
      "text": "Amendment SA 1738 agreed to in Senate by Voice Vote.", 
      "type": "vote", 
      "vote_type": "vote", 
      "where": "s"
    }
  ], 
  "amendment_id": "samdt1738-109", 
  "amendment_type": "samdt", 
  "amends_amendment": null, 
  "amends_bill": {
    "bill_id": "hr2744-109", 
    "bill_type": "hr", 
    "congress": 109, 
    "number": 2744
  }, 
  "amends_treaty": null, 
  "chamber": "s", 
  "congress": "109", 
  "description": null, 
  "introduced_at": "2005-09-20", 
  "number": 1738, 
  "proposed_at": "2005-09-20", 
  "purpose": "To express the sense of the Senate on the importation into the United States of beef from Japan.", 
  "sponsor": {
    "district": null, 
    "name": "Allard, Wayne", 
    "state": "CO", 
    "thomas_id": "00011", 
    "title": "Sen", 
    "type": "person"
  }, 
  "status": "pass", 
  "status_at": "2005-09-20", 
  "updated_at": "2013-07-17T08:16:11-04:00"
}