<bill session="106" type="h" number="3372" updated="2013-07-14T18:54:22-04:00">
  <state datetime="1999-11-15">REFERRED</state>
  <status>
    <introduced datetime="1999-11-15"/>
  </status>
  <introduced datetime="1999-11-15"/>
  <titles>
    <title as="introduced" type="short">Safe and Effective Breast Pumps Act</title>
    <title as="introduced" type="official">To establish a performance standard for breast pumps to facilitate their regulation under the Federal Food, Drug and Cosmetic Act, and for other purposes.</title>
  </titles>
  <sponsor id="400251"/>
  <cosponsors>
    <cosponsor id="400008" joined="2000-09-06"/>
    <cosponsor id="400525" joined="2000-09-13"/>
    <cosponsor id="400080" joined="1999-11-15"/>
    <cosponsor id="400087" joined="1999-11-15"/>
    <cosponsor id="400524" joined="1999-11-15"/>
    <cosponsor id="400370" joined="1999-11-15"/>
  </cosponsors>
  <actions>
    <action state="REFERRED" datetime="1999-11-15">
      <text>Referred to the House Committee on Commerce.</text>
    </action>
    <action datetime="1999-11-30">
      <text>Referred to the Subcommittee on Health and Environment.</text>
      <committee name="House Committee on Commerce"/>
    </action>
  </actions>
  <committees>
    <committee code="HSIF" name="House Commerce" activity="Referral, In Committee"/>
    <committee activity="Referral" code="HSIF04" subcommittee="Health and Environment" name="House Commerce"/>
  </committees>
  <relatedbills/>
  <subjects>
    <term name="Health"/>
    <term name="Administrative procedure"/>
    <term name="Breast feeding"/>
    <term name="Department of Health and Human Services"/>
    <term name="Equipment and supplies"/>
    <term name="Families"/>
    <term name="Government operations and politics"/>
    <term name="Government publications"/>
    <term name="Labor and employment"/>
    <term name="Law"/>
    <term name="Medical supplies"/>
    <term name="Standards"/>
    <term name="Women"/>
    <term name="Women's employment"/>
  </subjects>
  <amendments/>
  <summary>11/15/1999--Introduced.
Safe and Effective Breast Pumps Act - Directs the Secretary of Health and Human Services: (1) to put into effect a performance standard for breast pumps irrespective of the class to which the breast pumps have been classified under the Federal Food, Drug, and Cosmetic Act; (2) in establishing such standard, to identify those pumps appropriate for use on a regular basis in a place of employment based on the efficiency and effectiveness of the pump and on sanitation factors related to communal use; and (3) acting through the Commissioner of Food and Drugs, to issue a compliance policy guide which will assure that women who want to breastfeed a child are given full and complete information respecting breast pumps.</summary>
</bill>
