{
  "actions": [
    {
      "acted_at": "2012-07-18T17:21:00-04:00", 
      "references": [
        {
          "reference": "CR H4956-4957", 
          "type": "consideration"
        }, 
        {
          "reference": "CR H4957", 
          "type": "text"
        }
      ], 
      "text": "Amendment (A009) offered by Mr. Langevin.", 
      "type": "action"
    }, 
    {
      "acted_at": "2012-07-18T17:24:00-04:00", 
      "how": "by voice vote", 
      "references": [], 
      "result": "pass", 
      "text": "On agreeing to the Langevin amendment Agreed to by voice vote.", 
      "type": "vote", 
      "vote_type": "vote", 
      "where": "h"
    }
  ], 
  "amendment_id": "hamdt1386-112", 
  "amendment_type": "hamdt", 
  "amends_amendment": null, 
  "amends_bill": {
    "bill_id": "hr5856-112", 
    "bill_type": "hr", 
    "congress": 112, 
    "number": 5856
  }, 
  "amends_treaty": null, 
  "chamber": "h", 
  "congress": "112", 
  "description": "Amendment reduces the Operation and Maintenance, Defense-Wide account by $15 million and increases the funding for Defense Health Program by a similar amount for the purpose of augmenting the Spinal Cord Injury Research Program within the Congressionally Directed Medical Research Program.", 
  "house_number": 9, 
  "introduced_at": "2012-07-18", 
  "number": 1386, 
  "purpose": "An amendment numbered 6 printed in the Congressional Record to reduce the Operation and Maintenance, Defense-Wide account by $15 million and increase the Other Department of Defense Programs Defense Health Program by $15 million.", 
  "sponsor": {
    "district": "2", 
    "name": "Langevin, James R.", 
    "state": "RI", 
    "thomas_id": "01668", 
    "title": "Rep", 
    "type": "person"
  }, 
  "status": "pass", 
  "status_at": "2012-07-18T17:24:00-04:00", 
  "updated_at": "2013-07-17T08:17:27-04:00"
}