{
  "actions": [
    {
      "acted_at": "1998-08-05T15:52:00-04:00", 
      "references": [], 
      "text": "Amendment (A029) offered by Mr. Conyers.", 
      "type": "action"
    }, 
    {
      "acted_at": "1998-08-05T16:00:00-04:00", 
      "references": [], 
      "text": "Mr. Hutchinson raised a point of order against the Conyers amendment (A029). Mr. Hutchinson stated that the Conyers amendment expands the scope and includes new legislative language. Point of order overruled by the Chair.", 
      "type": "action"
    }, 
    {
      "acted_at": "1998-08-05T18:12:00-04:00", 
      "references": [], 
      "text": "On agreeing to the Conyers amendment (A029) Agreed to by recorded vote: 249 - 182 (Roll No. 396).", 
      "type": "action"
    }
  ], 
  "amendment_id": "hamdt853-105", 
  "amendment_type": "hamdt", 
  "amends_amendment": null, 
  "amends_bill": {
    "bill_id": "hr4276-105", 
    "bill_type": "hr", 
    "congress": 105, 
    "number": 4276
  }, 
  "amends_treaty": null, 
  "chamber": "h", 
  "congress": "105", 
  "description": "Amendment clarifies that any independent counsel appointed under title 28 of the United States Code and any employee of such independent counsel is covered under title 8 of the bill which establishes ethical standards for Federal prosecutors.", 
  "house_number": 29, 
  "introduced_at": "1998-08-05", 
  "number": 853, 
  "purpose": "An amendment to include any independent counsel appointed under title 28, United States Code, in the provisions of Title VIII, Citizens Protection, cited as the \"Citizens Protection Act of 1998.\"", 
  "sponsor": {
    "district": "14", 
    "name": "Conyers, John, Jr.", 
    "state": "MI", 
    "thomas_id": "00229", 
    "title": "Rep", 
    "type": "person"
  }, 
  "status": "offered", 
  "status_at": "1998-08-05", 
  "updated_at": "2013-07-17T07:51:43-04:00"
}