{
  "actions": [
    {
      "acted_at": "1996-06-05T17:52:00-04:00", 
      "references": [], 
      "text": "Amendment (A013) offered by Ms. Waters.", 
      "type": "action"
    }, 
    {
      "acted_at": "1996-06-05T17:57:00-04:00", 
      "references": [], 
      "text": "Mr. Callahan raised a point of order against the Waters amendment (A013). Mr. Callahan stated that the amendment would appropriate funds without authorization and was, therefore, in violation of the rules of the House. The Chair sustained the point of order.", 
      "type": "action"
    }
  ], 
  "amendment_id": "hamdt1124-104", 
  "amendment_type": "hamdt", 
  "amends_amendment": null, 
  "amends_bill": {
    "bill_id": "hr3540-104", 
    "bill_type": "hr", 
    "congress": 104, 
    "number": 3540
  }, 
  "amends_treaty": null, 
  "chamber": "h", 
  "congress": "104", 
  "description": null, 
  "house_number": 13, 
  "introduced_at": "1996-06-05", 
  "number": 1124, 
  "purpose": "An amendment, printed as amendment No. 74 in the Congressional Record of June 4, 1996, to reduce funds appropriated in the bill for the Asian Development Bank by $8 million and the Asian Development Fund by $25 million; and to restore funding by an equal amount for the African Development Bank and the African Development Fund.", 
  "sponsor": {
    "district": "35", 
    "name": "Waters, Maxine", 
    "state": "CA", 
    "thomas_id": "01205", 
    "title": "Rep", 
    "type": "person"
  }, 
  "status": "offered", 
  "status_at": "1996-06-05", 
  "updated_at": "2013-07-17T07:50:55-04:00"
}