{
  "actions": [
    {
      "acted_at": "2012-09-20T19:14:00-04:00", 
      "references": [
        {
          "reference": "CR H6217-6218", 
          "type": "consideration"
        }, 
        {
          "reference": "CR H6217", 
          "type": "text"
        }
      ], 
      "text": "Amendment (A006) offered by Mr. Benishek.", 
      "type": "action"
    }, 
    {
      "acted_at": "2012-09-20T19:19:00-04:00", 
      "how": "by voice vote", 
      "references": [], 
      "result": "pass", 
      "text": "On agreeing to the Benishek amendment (A006) Agreed to by voice vote.", 
      "type": "vote", 
      "vote_type": "vote", 
      "where": "h"
    }
  ], 
  "amendment_id": "hamdt1488-112", 
  "amendment_type": "hamdt", 
  "amends_amendment": null, 
  "amends_bill": {
    "bill_id": "hr3409-112", 
    "bill_type": "hr", 
    "congress": 112, 
    "number": 3409
  }, 
  "amends_treaty": null, 
  "chamber": "h", 
  "congress": "112", 
  "description": "Amendment requires the Committee for the Cumulative Analysis of Regulations that Impact Energy and Manufacturing in the United States to include the health effects associated with regulatory costs in its assessment.", 
  "house_number": 6, 
  "introduced_at": "2012-09-20", 
  "number": 1488, 
  "purpose": "An amendment numbered 6 printed in House Report 112-680 to require the Committee for the Cumulative Analysis of Regulations that Impact Energy and Manufacturing in the United States to include the health effects associated with regulatory costs in its assessment.", 
  "sponsor": {
    "district": "1", 
    "name": "Benishek, Dan", 
    "state": "MI", 
    "thomas_id": "02027", 
    "title": "Rep", 
    "type": "person"
  }, 
  "status": "pass", 
  "status_at": "2012-09-20T19:19:00-04:00", 
  "updated_at": "2013-07-17T08:17:29-04:00"
}