<bill session="108" type="h" number="2481" updated="2013-07-14T19:01:31-04:00">
  <state datetime="2003-06-16">REFERRED</state>
  <status>
    <introduced datetime="2003-06-16"/>
  </status>
  <introduced datetime="2003-06-16"/>
  <titles>
    <title as="introduced" type="short">Estate Tax Reduction Act of 2003</title>
    <title as="introduced" type="official">To amend the Internal Revenue Code of 1986 to reduce estate tax rates by 20 percent, to increase the unified credit against estate and gift taxes to the equivalent of a $2,500,000 exclusion and to provide an inflation adjustment of such amount, and for other purposes.</title>
  </titles>
  <sponsor id="400246"/>
  <cosponsors/>
  <actions>
    <action state="REFERRED" datetime="2003-06-16">
      <text>Referred to the House Committee on Ways and Means.</text>
    </action>
  </actions>
  <committees>
    <committee code="HSWM" name="House Ways and Means" activity="Referral, In Committee"/>
  </committees>
  <relatedbills/>
  <subjects>
    <term name="Taxation"/>
    <term name="Cost of living adjustments"/>
    <term name="Economics and public finance"/>
    <term name="Estate tax"/>
    <term name="Gift tax"/>
    <term name="Indexing (Economic policy)"/>
    <term name="Tax credits"/>
    <term name="Tax rates"/>
  </subjects>
  <amendments/>
  <summary>6/16/2003--Introduced.
Estate Tax Reduction Act of 2003 - Amends the Internal Revenue Code to: (1) reduce estate tax rates; (2) repeal the phaseout of graduated rates; and (3) increase the unified credit to $2.5 million, with an inflation adjustment.</summary>
</bill>
