{
  "actions": [
    {
      "acted_at": "2008-06-11T13:21:00-04:00", 
      "references": [
        {
          "reference": "CR H5259-5260", 
          "type": "consideration"
        }, 
        {
          "reference": "CR H5259", 
          "type": "text"
        }
      ], 
      "text": "Amendment (A007) offered by Mr. Murphy, Patrick.", 
      "type": "action"
    }, 
    {
      "acted_at": "2008-06-11T13:28:00-04:00", 
      "how": "by voice vote", 
      "references": [], 
      "result": "pass", 
      "text": "On agreeing to the Murphy, Patrick amendment (A007) Agreed to by voice vote.", 
      "type": "vote", 
      "vote_type": "vote", 
      "where": "h"
    }
  ], 
  "amendment_id": "hamdt1083-110", 
  "amendment_type": "hamdt", 
  "amends_amendment": null, 
  "amends_bill": {
    "bill_id": "hr6003-110", 
    "bill_type": "hr", 
    "congress": 110, 
    "number": 6003
  }, 
  "amends_treaty": null, 
  "chamber": "h", 
  "congress": "110", 
  "description": "Amendment requires Amtrak, within one year of enactment, to report to Congress on the results of an evaluation of passenger rail between Cornwells Heights, PA, and New York City, NY, and between Princeton Junction, NJ, and New York City, NY, to determine whether to expand passenger rail service by increasing the frequency of stops or reducing commuter ticket prices for this route.", 
  "house_number": 7, 
  "introduced_at": "2008-06-11", 
  "number": 1083, 
  "purpose": "An amendment numbered 8 printed in House Report 110-703 to require Amtrak, within one year of enactment, to report to Congress on the results of an evaluation of passenger rail between Cornwells Heights, PA, and New York City, NY, and between Princeton Junction, NJ, and New York City, NY, to determine whether to expand passenger rail service by increasing the frequency of stops or reducing commuter ticket prices for this route.", 
  "sponsor": {
    "district": "8", 
    "name": "Murphy, Patrick J.", 
    "state": "PA", 
    "thomas_id": "01875", 
    "title": "Rep", 
    "type": "person"
  }, 
  "status": "pass", 
  "status_at": "2008-06-11T13:28:00-04:00", 
  "updated_at": "2013-07-17T08:16:33-04:00"
}