{
  "actions": [
    {
      "acted_at": "2012-03-27T17:21:00-04:00", 
      "references": [
        {
          "reference": "CR H1624", 
          "type": "consideration"
        }, 
        {
          "reference": "CR H1624", 
          "type": "text"
        }
      ], 
      "text": "Amendment (A007) offered by Ms. Eshoo.", 
      "type": "action"
    }, 
    {
      "acted_at": "2012-03-27T17:22:00-04:00", 
      "references": [
        {
          "reference": "CR H1624", 
          "type": "text as modified"
        }
      ], 
      "text": "Eshoo amendment (A007) modified by unanimous consent. Amendment inserts a new section regarding communications of first responders.", 
      "type": "action"
    }, 
    {
      "acted_at": "2012-03-27T17:23:00-04:00", 
      "references": [], 
      "text": "On agreeing to the Eshoo amendment (A007) as modified Agreed to by voice vote.", 
      "type": "action"
    }
  ], 
  "amendment_id": "hamdt998-112", 
  "amendment_type": "hamdt", 
  "amends_amendment": null, 
  "amends_bill": {
    "bill_id": "hr3309-112", 
    "bill_type": "hr", 
    "congress": 112, 
    "number": 3309
  }, 
  "amends_treaty": null, 
  "chamber": "h", 
  "congress": "112", 
  "description": null, 
  "house_number": 7, 
  "introduced_at": "2012-03-27", 
  "number": 998, 
  "purpose": "An amendment numbered 10 printed in House Report 112-422 to express that nothing in this Act shall impede the FCC from providing efficient and effective communication systems for state and local first responders.", 
  "sponsor": {
    "district": "14", 
    "name": "Eshoo, Anna G.", 
    "state": "CA", 
    "thomas_id": "00355", 
    "title": "Rep", 
    "type": "person"
  }, 
  "status": "offered", 
  "status_at": "2012-03-27", 
  "updated_at": "2013-07-17T08:17:20-04:00"
}