{
  "actions": [
    {
      "acted_at": "2012-06-06T21:17:00-04:00", 
      "references": [
        {
          "reference": "CR H3548-3549", 
          "type": "consideration"
        }, 
        {
          "reference": "CR H3548", 
          "type": "text"
        }
      ], 
      "text": "Amendment (A017) offered by Mr. Cravaack.", 
      "type": "action"
    }, 
    {
      "acted_at": "2012-06-06T21:23:00-04:00", 
      "how": "by voice vote", 
      "references": [], 
      "result": "pass", 
      "text": "On agreeing to the Cravaack amendment (A017) Agreed to by voice vote.", 
      "type": "vote", 
      "vote_type": "vote", 
      "where": "h"
    }
  ], 
  "amendment_id": "hamdt1248-112", 
  "amendment_type": "hamdt", 
  "amends_amendment": null, 
  "amends_bill": {
    "bill_id": "hr5855-112", 
    "bill_type": "hr", 
    "congress": 112, 
    "number": 5855
  }, 
  "amends_treaty": null, 
  "chamber": "h", 
  "congress": "112", 
  "description": "Amendment redirects $10 million in funding within the Transportation Security Administration Aviation Security account for the Federal Flight Deck Officer program.", 
  "house_number": 17, 
  "introduced_at": "2012-06-06", 
  "number": 1248, 
  "purpose": "An amendment to redirect $10 million in funding within the Transportation Security Administration Aviation Security account.", 
  "sponsor": {
    "district": "8", 
    "name": "Cravaack, Chip", 
    "state": "MN", 
    "thomas_id": "02031", 
    "title": "Rep", 
    "type": "person"
  }, 
  "status": "pass", 
  "status_at": "2012-06-06T21:23:00-04:00", 
  "updated_at": "2013-07-17T08:17:21-04:00"
}