{
  "actions": [
    {
      "acted_at": "1997-04-23T14:24:00-04:00", 
      "references": [], 
      "text": "Amendment (A003) offered by Mr. Campbell.", 
      "type": "action"
    }, 
    {
      "acted_at": "1997-04-23T17:26:00-04:00", 
      "how": "roll", 
      "references": [], 
      "result": "fail", 
      "roll": 86, 
      "text": "On agreeing to the Campbell amendment (A003) Failed by recorded vote: 185 - 224 (Roll no. 86).", 
      "type": "vote", 
      "vote_type": "vote", 
      "where": "h"
    }
  ], 
  "amendment_id": "hamdt27-105", 
  "amendment_type": "hamdt", 
  "amends_amendment": null, 
  "amends_bill": {
    "bill_id": "hr400-105", 
    "bill_type": "hr", 
    "congress": 105, 
    "number": 400
  }, 
  "amends_treaty": null, 
  "chamber": "h", 
  "congress": "105", 
  "description": "Amendment sought to limit the defense to patent infringement based on prior domestic use, to the actual quantity, volume, or scope of the prior use.", 
  "house_number": 3, 
  "introduced_at": "1997-04-23", 
  "number": 27, 
  "purpose": "An amendment, printed as amendment No. 1 in the Congressional Record of April 16, 1997, to limit the extent to which prior commercial users of subsequently patented inventions without paying royalties. The amendment would restrict prior use to the scope and volume of use prior to the time a patent was granted.", 
  "sponsor": {
    "district": "15", 
    "name": "Campbell, Tom", 
    "state": "CA", 
    "thomas_id": "00170", 
    "title": "Rep", 
    "type": "person"
  }, 
  "status": "fail", 
  "status_at": "1997-04-23T17:26:00-04:00", 
  "updated_at": "2013-07-17T07:51:33-04:00"
}