<bill session="108" type="hc" number="451" updated="2013-07-14T19:03:11-04:00">
  <state datetime="2004-06-16">REFERRED</state>
  <status>
    <introduced datetime="2004-06-16"/>
  </status>
  <introduced datetime="2004-06-16"/>
  <titles>
    <title as="introduced" type="official">Expressing the sense of Congress regarding the establishment of a scholarship fund to make tuition grants available to eligible former students who were denied an education in Prince Edward County, Virginia, when the public schools closed rather than comply with the Supreme Court's decision in Brown v. Board of Education.</title>
  </titles>
  <sponsor id="400199"/>
  <cosponsors>
    <cosponsor id="400048" joined="2004-06-16"/>
    <cosponsor id="400074" joined="2004-06-16"/>
    <cosponsor id="400204" joined="2004-06-16"/>
    <cosponsor id="400208" joined="2004-06-16"/>
    <cosponsor id="400217" joined="2004-06-16"/>
    <cosponsor id="400227" joined="2004-06-16"/>
    <cosponsor id="400240" joined="2004-06-16"/>
    <cosponsor id="400271" joined="2004-06-16"/>
    <cosponsor id="400350" joined="2004-06-16"/>
    <cosponsor id="400360" joined="2004-06-16"/>
    <cosponsor id="400364" joined="2004-06-16"/>
    <cosponsor id="400384" joined="2004-06-16"/>
    <cosponsor id="400409" joined="2004-06-16"/>
    <cosponsor id="400423" joined="2004-06-16"/>
  </cosponsors>
  <actions>
    <action state="REFERRED" datetime="2004-06-16">
      <text>Referred to the House Committee on Education and the Workforce.</text>
    </action>
    <action datetime="2004-07-15">
      <text>Referred to the Subcommittee on Education Reform.</text>
      <committee name="House Committee on Education and the Workforce"/>
    </action>
  </actions>
  <committees>
    <committee code="HSED" name="House Education and the Workforce" activity="Referral, In Committee"/>
    <committee activity="Referral" code="HSED14" subcommittee="Education Reform" name="House Education and the Workforce"/>
  </committees>
  <relatedbills/>
  <subjects>
    <term name="Education"/>
    <term name="Civil rights and liberties, minority issues"/>
    <term name="Desegregation in education"/>
    <term name="Discrimination in education"/>
    <term name="Economics and public finance"/>
    <term name="Elementary and secondary education"/>
    <term name="Elementary education"/>
    <term name="Government operations and politics"/>
    <term name="Government trust funds"/>
    <term name="Law"/>
    <term name="Minorities"/>
    <term name="Minority education"/>
    <term name="Racial discrimination"/>
    <term name="Scholarships"/>
    <term name="Secondary education"/>
    <term name="State finance"/>
    <term name="Supreme Court decisions"/>
    <term name="Virginia"/>
  </subjects>
  <amendments/>
  <summary>6/16/2004--Introduced.
Expresses the sense of the Congress that the State of Virginia should provide the necessary resources to establish and maintain a scholarship fund to make tuition grants available to eligible former students who were denied an education in Prince Edward County, Virginia, when the public schools there closed rather than comply with the Supreme Court's decision in Brown v. Board of Education.</summary>
</bill>
