{
  "actions": [
    [
      "Floor Action", 
      "January 22, 2013", 
      "Received in the Senate and referred to the Committee on Foreign Relations."
    ], 
    [
      "Committee Action", 
      "January 24, 2013", 
      "Committee on Foreign Relations. Hearings held."
    ], 
    [
      "Committee Action", 
      "January 29, 2013", 
      "Committee on Foreign Relations. Ordered to be reported favorably."
    ], 
    [
      "Floor Action", 
      "January 29, 2013", 
      "Reported by Senator Menendez, Committee on Foreign Relations, without printed report."
    ], 
    [
      "Floor Action", 
      "January 29, 2013", 
      "Placed on Senate Executive Calendar. Calendar No. 1. Subject to nominee's commitment to respond to requests to appear and testify before any duly constituted committee of the Senate."
    ], 
    [
      "Floor Action", 
      "January 29, 2013", 
      "By unanimous consent agreement, debate and vote today."
    ], 
    [
      "Floor Action", 
      "January 29, 2013", 
      "Considered by Senate."
    ], 
    [
      "Floor Action", 
      "January 29, 2013", 
      "Confirmed by the Senate by Yea-Nay Vote. 94"
    ]
  ], 
  "congress": 113, 
  "control number": "113PN0004200", 
  "date": "2013-01-22", 
  "date received": "January 22, 2013 (113th Congress)", 
  "name": "John Forbes Kerry", 
  "nomination": "PN42-113", 
  "nomination_id": "PN42-113", 
  "nominee": "John Forbes Kerry, of Massachusetts, to be Secretary of State", 
  "organization": "Department of State", 
  "parsed": [
    "Kerry", 
    "John", 
    " Forbes"
  ], 
  "position": "Secretary of State", 
  "referred to": "Senate Foreign Relations", 
  "reported by": "Senate Foreign Relations", 
  "st_abbr": "MA", 
  "state": "Massachusetts"
}