{
  "actions": [
    {
      "acted_at": "2008-09-26T20:33:00-04:00", 
      "references": [], 
      "text": "Amendment (A002) offered by Mr. Andrews.", 
      "type": "action"
    }, 
    {
      "acted_at": "2008-09-26T20:33:00-04:00", 
      "how": "without objection", 
      "references": [], 
      "result": "pass", 
      "text": "On agreeing to the Andrews amendment (A002) Agreed to without objection.", 
      "type": "vote", 
      "vote_type": "vote", 
      "where": "h"
    }
  ], 
  "amendment_id": "hamdt1192-110", 
  "amendment_type": "hamdt", 
  "amends_amendment": null, 
  "amends_bill": {
    "bill_id": "hconres239-110", 
    "bill_type": "hconres", 
    "congress": 110, 
    "number": 239
  }, 
  "amends_treaty": null, 
  "chamber": "h", 
  "congress": "110", 
  "description": "Amendment inserted a new preamble.", 
  "house_number": 2, 
  "introduced_at": "2008-09-26", 
  "number": 1192, 
  "purpose": "Amendment inserted a new preamble.", 
  "sponsor": {
    "district": "1", 
    "name": "Andrews, Robert E.", 
    "state": "NJ", 
    "thomas_id": "00021", 
    "title": "Rep", 
    "type": "person"
  }, 
  "status": "pass", 
  "status_at": "2008-09-26T20:33:00-04:00", 
  "updated_at": "2013-07-17T08:16:33-04:00"
}