{
  "actions": [
    {
      "acted_at": "1997-11-05T11:36:00-05:00", 
      "references": [], 
      "text": "Amendment (A001) in the nature of a substitute considered as adopted pursuant to the provisions of H. Res. 303.", 
      "type": "action"
    }, 
    {
      "acted_at": "1997-11-05T11:37:00-05:00", 
      "references": [], 
      "text": "Ways and Means amendment (A001) modified by unanimous consent.", 
      "type": "action"
    }, 
    {
      "acted_at": "1997-11-05T11:38:00-05:00", 
      "references": [], 
      "text": "On agreeing to the Ways and Means amendment (A001) as modified Agreed to without objection.", 
      "type": "action"
    }
  ], 
  "amendment_id": "hamdt457-105", 
  "amendment_type": "hamdt", 
  "amends_amendment": null, 
  "amends_bill": {
    "bill_id": "hr2676-105", 
    "bill_type": "hr", 
    "congress": 105, 
    "number": 2676
  }, 
  "amends_treaty": null, 
  "chamber": "h", 
  "congress": "105", 
  "description": null, 
  "house_number": 1, 
  "introduced_at": "1997-11-05", 
  "number": 457, 
  "purpose": "An amendment in the nature of a substitute recommended by the Committee on Ways and Means now printed in the bill, as modified by the amendments printed in House Report 105-380, and considered as adopted pursuant to H. Res. 303.", 
  "sponsor": {
    "committee_id": "hswm00", 
    "name": "House Ways and Means", 
    "type": "committee"
  }, 
  "status": "offered", 
  "status_at": "1997-11-05", 
  "updated_at": "2013-07-17T07:51:38-04:00"
}