{
  "actions": [
    {
      "acted_at": "2006-03-16", 
      "references": [
        {
          "reference": "CR S2271-2272", 
          "type": "consideration"
        }, 
        {
          "reference": "CR S2271", 
          "type": "text"
        }
      ], 
      "text": "Amendment SA 3167 proposed by Senator Gregg for Senator Brownback.", 
      "type": "action"
    }, 
    {
      "acted_at": "2006-03-16", 
      "how": "Unanimous Consent", 
      "references": [], 
      "result": "pass", 
      "text": "Amendment SA 3167 agreed to in Senate by Unanimous Consent.", 
      "type": "vote", 
      "vote_type": "vote", 
      "where": "s"
    }
  ], 
  "amendment_id": "samdt3167-109", 
  "amendment_type": "samdt", 
  "amends_amendment": null, 
  "amends_bill": {
    "bill_id": "sconres83-109", 
    "bill_type": "sconres", 
    "congress": 109, 
    "number": 83
  }, 
  "amends_treaty": null, 
  "chamber": "s", 
  "congress": "109", 
  "description": null, 
  "introduced_at": "2006-03-16", 
  "number": 3167, 
  "proposed_at": "2006-03-16", 
  "purpose": "To establish a reserve fund for a Commission for Accountability and Review of Federal Agencies.", 
  "sponsor": {
    "district": null, 
    "name": "Brownback, Sam", 
    "state": "KS", 
    "thomas_id": "00137", 
    "title": "Sen", 
    "type": "person"
  }, 
  "status": "pass", 
  "status_at": "2006-03-16", 
  "updated_at": "2013-07-17T08:16:14-04:00"
}