{
  "actions": [
    {
      "acted_at": "2000-07-20T16:49:00-04:00", 
      "references": [
        {
          "reference": "CR H6653-6654", 
          "type": "consideration"
        }, 
        {
          "reference": "CR H6653", 
          "type": "text"
        }
      ], 
      "text": "Amendment (A005) offered by Mr. Wynn.", 
      "type": "action"
    }, 
    {
      "acted_at": "2000-07-20T16:54:00-04:00", 
      "references": [], 
      "text": "By unanimous consent, the Wynn amendment was withdrawn.", 
      "type": "action"
    }
  ], 
  "amendment_id": "hamdt1016-106", 
  "amendment_type": "hamdt", 
  "amends_amendment": null, 
  "amends_bill": {
    "bill_id": "hr4871-106", 
    "bill_type": "hr", 
    "congress": 106, 
    "number": 4871
  }, 
  "amends_treaty": null, 
  "chamber": "h", 
  "congress": "106", 
  "description": null, 
  "house_number": 5, 
  "introduced_at": "2000-07-20", 
  "number": 1016, 
  "purpose": "An amendment to add a new section providing for $101,000,000 by transfer for the design and construction or laboratory facilities for the Center for Drug Evaluation and Research, Food and Drug Administration.", 
  "sponsor": {
    "district": "4", 
    "name": "Wynn, Albert Russell", 
    "state": "MD", 
    "thomas_id": "01251", 
    "title": "Rep", 
    "type": "person"
  }, 
  "status": "offered", 
  "status_at": "2000-07-20", 
  "updated_at": "2013-07-17T08:15:44-04:00"
}