<bill session="108" type="h" number="693" updated="2013-07-14T19:00:45-04:00">
  <state datetime="2003-02-11">REFERRED</state>
  <status>
    <introduced datetime="2003-02-11"/>
  </status>
  <introduced datetime="2003-02-11"/>
  <titles>
    <title as="introduced" type="short">Military Death Gratuity Improvement Act of 2003</title>
    <title as="introduced" type="official">To amend the Internal Revenue Code of 1986 to exclude from gross income certain death gratuity payments to members of the uniformed services.</title>
  </titles>
  <sponsor id="400209"/>
  <cosponsors>
    <cosponsor id="400001" joined="2003-02-11"/>
    <cosponsor id="400003" joined="2003-02-11"/>
    <cosponsor id="400017" joined="2003-02-13"/>
    <cosponsor id="400039" joined="2003-02-11"/>
    <cosponsor id="400048" joined="2003-02-13"/>
    <cosponsor id="400057" joined="2003-02-11"/>
    <cosponsor id="400063" joined="2003-03-26"/>
    <cosponsor id="400073" joined="2003-02-25"/>
    <cosponsor id="400077" joined="2003-02-11"/>
    <cosponsor id="400080" joined="2003-10-02"/>
    <cosponsor id="400109" joined="2003-02-11"/>
    <cosponsor id="400114" joined="2003-04-07"/>
    <cosponsor id="400124" joined="2003-02-13"/>
    <cosponsor id="400127" joined="2003-02-11"/>
    <cosponsor id="400137" joined="2003-02-11"/>
    <cosponsor id="400140" joined="2003-02-11"/>
    <cosponsor id="400148" joined="2003-02-11"/>
    <cosponsor id="400150" joined="2003-02-13"/>
    <cosponsor id="400151" joined="2003-03-26"/>
    <cosponsor id="400164" joined="2003-02-25"/>
    <cosponsor id="400168" joined="2003-02-25"/>
    <cosponsor id="400172" joined="2003-02-11"/>
    <cosponsor id="400174" joined="2003-02-11"/>
    <cosponsor id="400177" joined="2003-05-15"/>
    <cosponsor id="400178" joined="2003-10-02"/>
    <cosponsor id="400183" joined="2003-10-02"/>
    <cosponsor id="400187" joined="2003-02-13"/>
    <cosponsor id="400195" joined="2003-03-18"/>
    <cosponsor id="400214" joined="2003-03-05"/>
    <cosponsor id="400224" joined="2003-02-11"/>
    <cosponsor id="400226" joined="2003-02-11"/>
    <cosponsor id="400231" joined="2003-02-11"/>
    <cosponsor id="400254" joined="2003-10-02"/>
    <cosponsor id="400256" joined="2003-02-11"/>
    <cosponsor id="400260" joined="2003-10-02"/>
    <cosponsor id="400269" joined="2003-02-11"/>
    <cosponsor id="400273" joined="2003-02-11"/>
    <cosponsor id="400279" joined="2003-02-11"/>
    <cosponsor id="400282" joined="2003-10-30"/>
    <cosponsor id="400302" joined="2003-02-11"/>
    <cosponsor id="400311" joined="2003-02-13"/>
    <cosponsor id="400321" joined="2003-02-25"/>
    <cosponsor id="400323" joined="2003-02-11"/>
    <cosponsor id="400337" joined="2003-02-11"/>
    <cosponsor id="400357" joined="2003-02-11"/>
    <cosponsor id="400361" joined="2003-02-27"/>
    <cosponsor id="400362" joined="2003-02-11"/>
    <cosponsor id="400375" joined="2003-02-11"/>
    <cosponsor id="400380" joined="2003-02-11"/>
    <cosponsor id="400383" joined="2003-02-11"/>
    <cosponsor id="400395" joined="2003-02-11"/>
    <cosponsor id="400396" joined="2003-02-11"/>
    <cosponsor id="400399" joined="2003-02-27"/>
    <cosponsor id="400400" joined="2003-02-11"/>
    <cosponsor id="400412" joined="2003-02-27"/>
    <cosponsor id="400432" joined="2003-10-02"/>
    <cosponsor id="400433" joined="2003-02-11"/>
  </cosponsors>
  <actions>
    <action state="REFERRED" datetime="2003-02-11">
      <text>Referred to the House Committee on Ways and Means.</text>
    </action>
    <action datetime="2003-07-22">
      <text>Sponsor introductory remarks on measure.</text>
      <reference ref="CR H7230"/>
    </action>
    <action datetime="2003-09-09">
      <text>Sponsor introductory remarks on measure.</text>
      <reference ref="CR H8019"/>
    </action>
  </actions>
  <committees>
    <committee code="HSWM" name="House Ways and Means" activity="Referral, In Committee"/>
  </committees>
  <relatedbills/>
  <subjects>
    <term name="Armed forces and national security"/>
    <term name="Families"/>
    <term name="Income tax"/>
    <term name="Labor and employment"/>
    <term name="Military pensions"/>
    <term name="Survivors' benefits"/>
    <term name="Tax exclusion"/>
    <term name="Taxation"/>
  </subjects>
  <amendments/>
  <summary>2/11/2003--Introduced.
Military Death Gratuity Improvement Act of 2003 - Revises provisions concerning the exclusion from gross income of any qualified military benefit to redefine the term "qualified military benefit" to mean any allowance or in-kind benefit (other than personal use of a vehicle) which: (1) is received by any member or former member of the uniformed services or any dependent of such member by reason of such member's status or service as a member of such uniformed services; and (2) was excludable from gross income on December 31, 1991, (currently, September 9, 1986) under any provision of law, regulation, or administrative practice which was in effect on such date. Makes such revision applicable in the case of a death gratuity payable under chapter 75 of title 10 of the United States Code, with respect to a death occurring after September 10, 2001.</summary>
</bill>
