{
  "actions": [
    {
      "acted_at": "2011-06-01T22:05:00-04:00", 
      "references": [
        {
          "reference": "CR H3892", 
          "type": "consideration"
        }, 
        {
          "reference": "CR H3892", 
          "type": "text"
        }
      ], 
      "text": "Amendment (A031) offered by Mr. Poe (TX).", 
      "type": "action"
    }, 
    {
      "acted_at": "2011-06-01T22:11:00-04:00", 
      "references": [], 
      "text": "Mr. Aderholt raised a point of order against the Poe (TX) amendment (A031). Mr. Aderholt stated that the amendment seeks to change existing law and constitutes legislation in an appropriationbill. The Chair sustained the point of order.", 
      "type": "action"
    }
  ], 
  "amendment_id": "hamdt379-112", 
  "amendment_type": "hamdt", 
  "amends_amendment": null, 
  "amends_bill": {
    "bill_id": "hr2017-112", 
    "bill_type": "hr", 
    "congress": 112, 
    "number": 2017
  }, 
  "amends_treaty": null, 
  "chamber": "h", 
  "congress": "112", 
  "description": null, 
  "house_number": 31, 
  "introduced_at": "2011-06-01", 
  "number": 379, 
  "purpose": "An amendment numbered 9 printed in the Congressional Record to prohibit the use of funds to provide to a State or local government entity or official that is in violation of section 642(a) of the Illegal Immigration Reform and Immigrant Responsibility Act of 1996.", 
  "sponsor": {
    "district": "2", 
    "name": "Poe, Ted", 
    "state": "TX", 
    "thomas_id": "01802", 
    "title": "Rep", 
    "type": "person"
  }, 
  "status": "offered", 
  "status_at": "2011-06-01", 
  "updated_at": "2013-07-17T08:17:17-04:00"
}