<bill session="104" type="h" number="3128" updated="2013-07-14T18:48:10-04:00">
  <state datetime="1996-03-20">REFERRED</state>
  <status>
    <introduced datetime="1996-03-20"/>
  </status>
  <introduced datetime="1996-03-20"/>
  <titles>
    <title as="introduced" type="official">To make it unlawful to send lobbying communications to Congress which are fraudulent.</title>
  </titles>
  <sponsor id="404142"/>
  <cosponsors>
    <cosponsor id="400110" joined="1996-03-20"/>
  </cosponsors>
  <actions>
    <action state="REFERRED" datetime="1996-03-20">
      <text>Referred to the House Committee on the Judiciary.</text>
    </action>
    <action datetime="1996-03-28">
      <text>Referred to the Subcommittee on the Constitution.</text>
      <committee name="House Committee on the Judiciary"/>
    </action>
  </actions>
  <committees>
    <committee code="HSJU" name="House Judiciary" activity="Referral, In Committee"/>
    <committee activity="Referral" code="HSJU10" subcommittee="Constitution" name="House Judiciary"/>
  </committees>
  <relatedbills/>
  <subjects>
    <term name="Congress"/>
    <term name="Advice and consent of the Senate"/>
    <term name="Electronic mail systems"/>
    <term name="Fines (Penalties)"/>
    <term name="Fraud"/>
    <term name="Government operations and politics"/>
    <term name="Legislation"/>
    <term name="Lobbying"/>
    <term name="Presidential appointments"/>
    <term name="Science, technology, communications"/>
    <term name="Telegraph"/>
  </subjects>
  <amendments/>
  <summary>3/20/1996--Introduced.
Subjects to a civil penalty not to exceed $50,000 any person who, with the intent to influence action by a House of Congress or any Member of Congress on any nomination or legislation makes a purported communication of the opinion of an identified individual respecting such action to a Member of Congress in any telegram, letter, or electronic communication knowing that such individual did not in fact authorize such communication.</summary>
</bill>
