{
  "actions": [
    {
      "acted_at": "2005-04-21T10:32:00-04:00", 
      "references": [
        {
          "reference": "CR H2401-2402", 
          "type": "consideration"
        }, 
        {
          "reference": "CR H2401-2402", 
          "type": "text"
        }
      ], 
      "text": "Amendment (A016) offered by Mr. Ford.", 
      "type": "action"
    }, 
    {
      "acted_at": "2005-04-21T10:38:00-04:00", 
      "how": "by voice vote", 
      "references": [], 
      "result": "pass", 
      "text": "On agreeing to the Ford amendment (A016) Agreed to by voice vote.", 
      "type": "vote", 
      "vote_type": "vote", 
      "where": "h"
    }
  ], 
  "amendment_id": "hamdt85-109", 
  "amendment_type": "hamdt", 
  "amends_amendment": null, 
  "amends_bill": {
    "bill_id": "hr6-109", 
    "bill_type": "hr", 
    "congress": 109, 
    "number": 6
  }, 
  "amends_treaty": null, 
  "chamber": "h", 
  "congress": "109", 
  "description": "Amendment requires the EPA to establish a program to encourage domestic production and sales of efficient hybrid and advanced diesel vehicles.", 
  "house_number": 16, 
  "introduced_at": "2005-04-21", 
  "number": 85, 
  "purpose": "An amendment numbered 16 printed in House Report 109-49 to authorize a total of $3 billion over ten years for a program to encourage the domestic production of hybrid and advanced vehicle diesel vehicles by providing grants to manufacturers and incentives to customers to purchase such vehicles.", 
  "sponsor": {
    "district": "9", 
    "name": "Ford, Harold E., Jr.", 
    "state": "TN", 
    "thomas_id": "01483", 
    "title": "Rep", 
    "type": "person"
  }, 
  "status": "pass", 
  "status_at": "2005-04-21T10:38:00-04:00", 
  "updated_at": "2013-07-17T08:16:17-04:00"
}